secret_agent/__init__.py
secret_agent/exceptions.py
secret_agent/secret_agent.py
secret_agent-23.12.2800.dist-info/METADATA
secret_agent-23.12.2800.dist-info/WHEEL
secret_agent-23.12.2800.dist-info/licenses/LICENSE
secret_agent-23.12.2800.dist-info/RECORD
