Metadata-Version: 2.1
Name: secret-agent
Version: 23.12.2800
Summary: An agent for handling secrets in config
Project-URL: Homepage, https://github.com/ghostdisco/secret-agent
Project-URL: Issues, https://github.com/ghostdisco/secret-agent/issues
Author-email: ghostdisco <pypi@ghostdisco.me>
License-File: LICENSE
Classifier: License :: OSI Approved :: BSD License
Classifier: Operating System :: OS Independent
Classifier: Programming Language :: Python :: 3
Requires-Python: >=3.8.1
Requires-Dist: cryptography>=41.0.7
